socceranalysis/__init__.py
socceranalysis/find_team_stat.py
socceranalysis/outlier_identification.py
socceranalysis/playerranking.py
socceranalysis/viz_stats.py
socceranalysis-0.1.6.dist-info/METADATA
socceranalysis-0.1.6.dist-info/WHEEL
socceranalysis-0.1.6.dist-info/LICENSE
socceranalysis-0.1.6.dist-info/RECORD
