Metadata-Version: 2.1
Name: socceranalysis
Version: 0.1.6
Summary: Doing soccer stats analysis.
Home-page: https://github.com/UBC-MDS/socceranalysis_python
License: MIT
Author: Group 15 
Requires-Python: >=3.9
Classifier: License :: OSI Approved :: MIT License
Classifier: Programming Language :: Python :: 3
Classifier: Programming Language :: Python :: 3.9
Classifier: Programming Language :: Python :: 3.10
Classifier: Programming Language :: Python :: 3.11
Requires-Dist: altair (>=4.2.0)
Requires-Dist: display (>=1.0.0,<2.0.0)
Requires-Dist: ipython (>=8.8.0,<9.0.0)
Requires-Dist: matplotlib (>=3.6.3)
Requires-Dist: numpy (>=1.24.1)
Requires-Dist: openpyxl (>=3.0.10)
Requires-Dist: pandas (>=1.5.2)
Requires-Dist: panel (>=0.14.2,<0.15.0)
Requires-Dist: python-semantic-release (>=7.33.0,<8.0.0)
Project-URL: Documentation, https://socceranalysis.readthedocs.io
Project-URL: Repository, https://github.com/UBC-MDS/socceranalysis_python
